<?xml version="1.0" encoding="utf-8" ?><transcript><text start="0.92" dur="5.24">[Music]</text><text start="4" dur="3.68">number five vikings what would a viking</text><text start="6.16" dur="3.6">be without his trusty battle helmet and</text><text start="7.68" dur="4.079">its impressive horns the answer is a</text><text start="9.76" dur="3.52">more historically accurate viking think</text><text start="11.759" dur="3.121">for a moment about what wearing headgear</text><text start="13.28" dur="2.88">like that into battle would mean the</text><text start="14.88" dur="2.56">horns are just easy targets for your</text><text start="16.16" dur="3.039">opponent to hit and knock off your</text><text start="17.44" dur="3.2">helmet or if you strap on your helmet</text><text start="19.199" dur="2.721">now your opponent has a convenient lever</text><text start="20.64" dur="2.639">with which to drag you to the ground and</text><text start="21.92" dur="3.84">something to hold onto while slitting</text><text start="23.279" dur="4.16">your throat horn helmets are a terrible</text><text start="25.76" dur="3.12">idea which is why archaeologists have</text><text start="27.439" dur="2.801">never found them at viking battle sites</text><text start="28.88" dur="3.12">and there&amp;#39;s no evidence that they were</text><text start="30.24" dur="3.28">ever used it was poets and artists</text><text start="32" dur="3.04">people not known for caring about facts</text><text start="33.52" dur="3.68">and reality who gave the vikings their</text><text start="35.04" dur="3.839">silly hats during the late 1800s long</text><text start="37.2" dur="3.199">after the vikings could correct their</text><text start="38.879" dur="3.601">misconceptions</text><text start="40.399" dur="3.84">number 4 lady godiva the story of this</text><text start="42.48" dur="3.36">11th century english noble woman is that</text><text start="44.239" dur="2.961">her mean husband the earl raised taxes</text><text start="45.84" dur="2.96">on the town&amp;#39;s people of coventry which</text><text start="47.2" dur="3.44">lady could die and not surprisingly the</text><text start="48.8" dur="3.36">locals thought were too high she</text><text start="50.64" dur="3.28">badgered her husband and he conceded in</text><text start="52.16" dur="3.28">exasperation to lower the taxes if she</text><text start="53.92" dur="3.68">rode through the town naked assuming</text><text start="55.44" dur="3.599">that she never would but she did because</text><text start="57.6" dur="2.799">people don&amp;#39;t like taxes even though</text><text start="59.039" dur="3.36">their house civilization is purchased</text><text start="60.399" dur="4.48">lady godiva&amp;#39;s story lives on notably in</text><text start="62.399" dur="4.241">the godiva logo and in popular songs but</text><text start="64.879" dur="3.441">while lady godiva was a real person and</text><text start="66.64" dur="3.28">coventry is a real town there&amp;#39;s no</text><text start="68.32" dur="3.36">record of her nude ride from the time</text><text start="69.92" dur="3.6">when it happened so we can safely assume</text><text start="71.68" dur="3.68">the story is false just as with the</text><text start="73.52" dur="3.68">vikings again poets and artists are to</text><text start="75.36" dur="3.92">blame who made it the tale long after</text><text start="77.2" dur="4.4">lady godiva&amp;#39;s death number three</text><text start="79.28" dur="3.76">napoleon famously this tiny tiny general</text><text start="81.6" dur="3.199">perhaps to compensate for his short</text><text start="83.04" dur="3.119">stature took control of france greatly</text><text start="84.799" dur="3.281">expanded its influence and dubbed</text><text start="86.159" dur="4.721">himself emperor napoleon&amp;#39;s official</text><text start="88.08" dur="4.32">height was indeed 5 foot 2 inches but at</text><text start="90.88" dur="2.879">the time french inches were longer than</text><text start="92.4" dur="2.88">english inches so during the unit</text><text start="93.759" dur="3.441">conversion napoleon&amp;#39;s height should have</text><text start="95.28" dur="3.76">been reported as 5 7 in england&amp;#39;s</text><text start="97.2" dur="3.279">imperial units which is short by today&amp;#39;s</text><text start="99.04" dur="4">standards but was average or slightly</text><text start="100.479" dur="3.841">above average in the early 1800s however</text><text start="103.04" dur="2.96">england with its eternal love of all</text><text start="104.32" dur="3.68">things french didn&amp;#39;t care and went with</text><text start="106" dur="4.079">the napoleon is so short lol version of</text><text start="108" dur="3.92">the story in newspapers and cartoons</text><text start="110.079" dur="3.36">meanwhile napoleon was busy introducing</text><text start="111.92" dur="2.8">the metric system to france in the wider</text><text start="113.439" dur="2.64">world to standardize measurements so</text><text start="114.72" dur="3.039">this sort of confusion would never</text><text start="116.079" dur="4.961">happen again and thankfully the whole</text><text start="117.759" dur="5.921">world now uses metric mostly sort of</text><text start="121.04" dur="4.16">number two roman vomit ah the roman</text><text start="123.68" dur="3.36">empire so great and powerful but</text><text start="125.2" dur="3.119">corrupted by decadence from within and</text><text start="127.04" dur="2.96">what could be a better symbol of that</text><text start="128.319" dur="3.121">decadence than the vomitorium where</text><text start="130" dur="3.28">romans after stuffing themselves with</text><text start="131.44" dur="4.08">delicious foods could vomit them all up</text><text start="133.28" dur="4">again to make room to feast anew</text><text start="135.52" dur="3.04">valmatoria are real but this idea of</text><text start="137.28" dur="3.039">them is not though the confusion is</text><text start="138.56" dur="3.52">understandable because their name vomit</text><text start="140.319" dur="3.601">aurium seems to make their purpose so</text><text start="142.08" dur="3.12">clear even if for some reason you know</text><text start="143.92" dur="2.56">latin perhaps because you live in a</text><text start="145.2" dur="2.72">country that insists you waste hundreds</text><text start="146.48" dur="2.96">of hours of your life learning a dead</text><text start="147.92" dur="3.039">useless language this knowledge still</text><text start="149.44" dur="4.079">won&amp;#39;t help you because the root word</text><text start="150.959" dur="4.081">vomitum means to spew forth so what is</text><text start="153.519" dur="3.601">it really if you&amp;#39;ve ever been to a big</text><text start="155.04" dur="4.559">stadium like say the ones made by the</text><text start="157.12" dur="4.399">romans you&amp;#39;ve already used a vomitorium</text><text start="159.599" dur="3.521">this is what the vomitoria are the</text><text start="161.519" dur="3.601">passageways that let lots of people</text><text start="163.12" dur="4">enter or exit at once the people are</text><text start="165.12" dur="4.24">what spews forth in the vomitoria not</text><text start="167.12" dur="4.32">the contents of the people number one</text><text start="169.36" dur="3.44">columbus there&amp;#39;s so very much wrong with</text><text start="171.44" dur="2.64">the common retelling of the story of</text><text start="172.8" dur="2.56">christopher columbus that it&amp;#39;s hard to</text><text start="174.08" dur="2.799">know where to begin but the biggest</text><text start="175.36" dur="3.04">misconception is that everyone else</text><text start="176.879" dur="3.041">thought the world was flat but columbus</text><text start="178.4" dur="3.6">was the only guy smart enough to know</text><text start="179.92" dur="3.52">that it&amp;#39;s round it makes a daring story</text><text start="182" dur="4.319">but knowledge of a spherical earth goes</text><text start="183.44" dur="5.36">back to at least 5000 bc that&amp;#39;s six and</text><text start="186.319" dur="4.56">a half thousand years before columbus</text><text start="188.8" dur="4.56">sets sail and that knowledge was never</text><text start="190.879" dur="3.921">lost to western civilization in 200 bc</text><text start="193.36" dur="3.04">eratosthenes calculated the earth&amp;#39;s</text><text start="194.8" dur="3.12">circumference and his estimate was still</text><text start="196.4" dur="3.6">well known and being used during</text><text start="197.92" dur="3.76">columbus&amp;#39;s time the argument columbus</text><text start="200" dur="3.599">had with queen isabella was not over the</text><text start="201.68" dur="3.68">shape of the earth but of its size</text><text start="203.599" dur="3.28">columbus estimated the earth was much</text><text start="205.36" dur="3.599">smaller than queen isabella and her</text><text start="206.879" dur="3.36">scientific advisors did which was why he</text><text start="208.959" dur="3.36">thought he could make it across the</text><text start="210.239" dur="3.92">empty atlantic to india but columbus&amp;#39;s</text><text start="212.319" dur="3.601">size estimate was wrong again just like</text><text start="214.159" dur="4.08">napoleon&amp;#39;s height because of mixed up</text><text start="215.92" dur="3.92">units however this mistake did send him</text><text start="218.239" dur="3.681">west to become the first european to</text><text start="219.84" dur="3.679">discover america as long as you ignore</text><text start="221.92" dur="4.599">the hornless vikings who beat him by 500</text><text start="223.519" dur="3">years</text><text start="237.76" dur="2.08">you</text></transcript>