{"uploaded_date":"2019/02/09","family_friendly":true,"channel_id":"UCfpCQ89W9wjkHc8J_6eTbBg","recommendations":[{"id":"11FLdubGdho","views":182447,"uploaded_date":"2019/04/18","channel_id":"UCfpCQ89W9wjkHc8J_6eTbBg","duration":901},{"id":"hS4Mso8gvNU","views":6261818,"uploaded_date":"2023/04/18","channel_id":"UCfpCQ89W9wjkHc8J_6eTbBg","duration":1998},{"id":"E8I_pUTxk_I","views":148465,"uploaded_date":"2025/03/18","channel_id":"UCso2Coek2uO1GVjOD_4CvMQ","duration":3985},{"id":"sSsTR8qqDl4","views":37269917,"uploaded_date":"2024/04/18","channel_id":"UCfpCQ89W9wjkHc8J_6eTbBg","duration":1676},{"id":"K3uiMsqptOs","views":4028585,"uploaded_date":"2024/04/18","channel_id":"UCOnnmKlDZltHAqJLz-XIpGA","duration":6960},{"id":"4begc_U8ygI","views":2250821,"uploaded_date":"2024/04/18","channel_id":"UCsE8PTncfn2Vga48jH46HnQ","duration":2198},{"id":"z_tf-YwkyqY","views":1039729,"uploaded_date":"2025/04/08","channel_id":"UCb0JxFSwHTzH0AEsAzQHV4w","duration":2019},{"id":"BwziJOvqFE0","views":3221407,"uploaded_date":"2025/04/14","channel_id":"UCtYKe7-XbaDjpUwcU5x0bLg","duration":1276},{"id":"yhfa4kpyMbs","views":1922330,"uploaded_date":"2025/03/18","channel_id":"UCmOCpBKeoBPp-HwarhIBA2g","duration":6247},{"id":"U_LlX4t0A9I","views":270288409,"uploaded_date":"2024/06/18","channel_id":"UCX6OQ3DkcsbYNE6H8uQQuVA","duration":1570},{"id":"tKKF-MJ-xvQ","views":8919296,"uploaded_date":"2024/04/18","channel_id":"UCfpCQ89W9wjkHc8J_6eTbBg","duration":1852},{"id":"BgWjgGbYxyk","views":12800360,"uploaded_date":"2024/08/18","channel_id":"UC-SuHonAEkrikvs2oj7LLXg","duration":11049},{"id":"jCGfYuX9ph8","views":3453589,"uploaded_date":"2020/04/18","channel_id":"UCzWn_gTaXyH5Idyo8Raf7_A","duration":1349},{"id":"meILZiqsJmc","views":268509,"uploaded_date":"2025/03/21","channel_id":"UCED-mVhtc9PDXcbAJne0tiQ","duration":1483},{"id":"OUaU2fUiBbY","views":2846592,"uploaded_date":"2024/08/18","channel_id":"UCQnmZZUKvpY3IVSGf44MVVg","duration":1909},{"id":"lcjdwSY2AzM","views":4591459,"uploaded_date":"2025/04/14","channel_id":"UCHnyfMqiRRG1u-2MsSQLbXA","duration":1660},{"id":"mP5i_abwmiY","views":133330,"uploaded_date":"2025/01/18","channel_id":"UCaULe1cc4jCQ6ZzUrDY81Sg","duration":4708},{"id":"o6zb6_TTVWo","views":36323679,"uploaded_date":"2024/04/18","channel_id":"UCfpCQ89W9wjkHc8J_6eTbBg","duration":1840},{"id":"NnwBa6Q2ANw","views":1717568,"uploaded_date":"2018/04/18","channel_id":"UCfpCQ89W9wjkHc8J_6eTbBg","duration":1439},{"id":"H42zWaD4A4s","views":94302643,"uploaded_date":"2025/02/18","channel_id":"UCWpk9PSGHoJW1hZT4egxTNQ","duration":1252}],"duration_s":1110,"id":"PvY0U68MIKg","channel_subscribers":1.44E7,"heatmap":[],"time_of_scraping_unix":1745026947,"views":124374,"keywords":["Fishing","Camping","Fishing in spain","Camping in Spain","Camping Europe","Fishing Europe","Spain Fishing","Catalonia","Catalonia fishing","Fishing and Camping","Fishing trip","Fishing and Camping in Spain","Spanish Fishing trip","Fishing for carp","Fishing for carp in Spain","Fishing ebro river","Fishing ebre river","Fishing for carp on the ebro river","trophy carp","carp fishing","bucket list carp fishing"],"title":"Fishing & Camping in Spain (Part 1)","chapters":[],"likes":2832,"description":"Me and Nathan flew to Barcelona Spain for a week of fishing and camping and adventures in Catalonia Spain. We had a great time fishing for trophy specimen carp on the Ebro River with fishing guide Nick Shattock. \n\nCheck out Nick Shattock's guide service website for more info. \nhttp://shattock.wixsite.com/ebrocarpfishing\n\nCheck out part 2 of our fishing & camping trip (Coming Soon)\n\nCheck out my other channel Catfish and Carp and see the fishing video from this trip. (Coming Soon)\n\nAnd click subscribe to the Outdoor Boys YouTube channel for new videos every Saturday morning. \nhttps://www.youtube.com/outdoorboys\n\nAlso check us out on Facebook and instagram\nhttps://www.facebook.com/TeamOutdoorBoys\n@outdoorboyschannel\n\nBUY OUTDOOR BOYS T-SHIRTS http://shop.spreadshirt.com/catsandcarp/ \nThe Video Editing Software is Sony Vegas 14.0 http://amzn.to/2zu7BAe \nCanon T5i (700D) http://amzn.to/2jcPFEi \nGoPro Hero 5+ Black http://amzn.to/2zuQnAI","is_live":false}