<?xml version="1.0" encoding="utf-8" ?><transcript><text start="0" dur="5.18">e</text><text start="2.09" dur="3.09">[Applause]</text><text start="11.98" dur="8.92">[Music]</text><text start="20.68" dur="5.18">[Applause]</text><text start="20.9" dur="5.28">[Music]</text><text start="25.86" dur="3.85">[Applause]</text><text start="26.18" dur="3.53">[Music]</text><text start="30.72" dur="2.84">all right here we</text><text start="35.52" dur="4.64">are uhoh we&amp;#39;re back here at our</text><text start="38.36" dur="3.76">Bushcraft survival shelter we got a</text><text start="40.16" dur="3.84">little problem one of our trees fell</text><text start="42.12" dur="4.56">over see how we have this tree here</text><text start="44" dur="5.399">supporting our cross members this one</text><text start="46.68" dur="7.08">fell over well looks like we better get</text><text start="49.399" dur="4.361">started we got a lot of work to do</text><text start="70.08" dur="6.28">Jacob you getting cold mhm all right</text><text start="72.68" dur="3.68">I&amp;#39;ll get a fire going</text><text start="103.079" dur="3">oh</text><text start="152.319" dur="2.361">when it&amp;#39;s snowing like this you got to</text><text start="153.44" dur="3.28">be really careful where you put your</text><text start="154.68" dur="6.08">tools down they&amp;#39;ll disappear and get</text><text start="156.72" dur="6.36">buried like that stuff gets lost really</text><text start="160.76" dur="4.6">easy when it&amp;#39;s snowing like this and you</text><text start="163.08" dur="3.84">won&amp;#39;t find it till Springtime got to</text><text start="165.36" dur="5">make sure you always put it somewhere</text><text start="166.92" dur="3.44">not in the snow</text><text start="188.68" dur="7.839">you&amp;#39;re lay out Hey Jake you like that</text><text start="192.959" dur="3.56">yeah yeah</text><text start="209.47" dur="3.05">[Music]</text><text start="243.04" dur="3">w</text><text start="279.02" dur="3.24">[Music]</text><text start="350.36" dur="2.559">do you see your</text><text start="353.08" dur="6.959">boot okay get down in</text><text start="357.199" dur="4.28">there all right well guys guys I&amp;#39;ve been</text><text start="360.039" dur="3.681">rushing like a mad man to get to this</text><text start="361.479" dur="4">point but we got to shelter up so we can</text><text start="363.72" dur="4.64">keep the snow off all of our gear which</text><text start="365.479" dur="4.361">is great cuz it was getting this wet and</text><text start="368.36" dur="4">I got the caught up it got a little bit</text><text start="369.84" dur="4.72">higher this time so I got room to put</text><text start="372.36" dur="3.679">the sled down here with their gear and I</text><text start="374.56" dur="4.039">got a little bed area that I&amp;#39;m going to</text><text start="376.039" dur="5">make for Jacob but we need to block the</text><text start="378.599" dur="6">wind and I need to put something over</text><text start="381.039" dur="8.081">here and over here and maybe over here</text><text start="384.599" dur="4.521">to make this a little bit more windproof</text><text start="414.46" dur="3.25">[Music]</text><text start="418.68" dur="2.84">o</text><text start="461.08" dur="6.36">a lot of wood cut but it&amp;#39;s all wet</text><text start="464.52" dur="5.239">covered in ice we got to prop it all up</text><text start="467.44" dur="2.319">by the</text><text start="471.96" dur="4.519">fire they&amp;#39;re so wet</text><text start="503.159" dur="6.401">Hey Jake how you doing are you</text><text start="506.039" dur="6.201">warm oh you&amp;#39;re super warm time to</text><text start="509.56" dur="2.68">transfer the</text><text start="516.2" dur="3.759">J there you go you like that is that is</text><text start="518.56" dur="4.76">that less Smokey</text><text start="519.959" dur="7.081">Jacob yeah that&amp;#39;s less Smokey you</text><text start="523.32" dur="5.28">feeling you feeling warm down there good</text><text start="527.04" dur="2.96">well it&amp;#39;s getting late I think the sun&amp;#39;s</text><text start="528.6" dur="3.32">going to set here in a little bit so I</text><text start="530" dur="6.36">think I better get some dinner made I</text><text start="531.92" dur="4.44">got a little boy who&amp;#39;s pretty hungry</text><text start="575.24" dur="3.36">open the fold</text><text start="622.839" dur="7.12">okay sit down on my</text><text start="625.88" dur="5.56">lap oh look at that meatball</text><text start="629.959" dur="5.921">I want</text><text start="631.44" dur="5.959">someu that good it&amp;#39;s spatti and</text><text start="635.88" dur="3.68">meatballs</text><text start="637.399" dur="6.521">with a</text><text start="639.56" dur="6.6">hwi oh yes you had a good time woo it&amp;#39;s</text><text start="643.92" dur="2.24">good</text><text start="651.24" dur="4.159">stuff you know it seems like every time</text><text start="653.36" dur="5.12">we go winter camping I burn up at least</text><text start="655.399" dur="4.841">one item I&amp;#39;m up to two so far this trip</text><text start="658.48" dur="4.2">I suck my water bottle by the fire to</text><text start="660.24" dur="5.52">keep it from freezing and U apparently I</text><text start="662.68" dur="5.839">stick it too close by the fire yeah it&amp;#39;s</text><text start="665.76" dur="4.56">got a goer now and check out Jacob&amp;#39;s</text><text start="668.519" dur="3.721">boot it was sitting here by the fire and</text><text start="670.32" dur="5.759">not only did it melt the tread but it</text><text start="672.24" dur="6.08">caught on fire it was yeah it was</text><text start="676.079" dur="4.32">bad</text><text start="678.32" dur="5.6">oh I can tell this is going to be an</text><text start="680.399" dur="3.521">expensive trip</text><text start="694.2" dur="3.8">got some very Frozen marshmallows</text><text start="698.32" dur="4.6">here warm cup of hot chocolate with a</text><text start="700.839" dur="4.041">marshmallow tastes pretty good on a</text><text start="702.92" dur="5.4">night like tonight got some hot</text><text start="704.88" dur="3.44">chocolate ready</text><text start="717.76" dur="6.879">yeah oh you you okay both out hot</text><text start="722.399" dur="4.361">sock well you know we&amp;#39;ve actually done</text><text start="724.639" dur="3.681">better with time management on this trip</text><text start="726.76" dur="3.639">than we have on others you know we&amp;#39;ve</text><text start="728.32" dur="3.44">got dinner done at a reasonable time and</text><text start="730.399" dur="3.56">we&amp;#39;ve got a bit of time to kill do you</text><text start="731.76" dur="6.639">want to watch a movie together</text><text start="733.959" dur="4.44">mhm we&amp;#39;re kicking it with old school</text><text start="739.959" dur="4.161">Transformers I have guns</text><text start="745.279" dur="4.601">coming we had a great time watching</text><text start="747.48" dur="4.159">shows together but Jake is out like a</text><text start="749.88" dur="4.079">light which is good it&amp;#39;s it&amp;#39;s fast as</text><text start="751.639" dur="4.121">bedtime but I got a few hours before I&amp;#39;m</text><text start="753.959" dur="4.24">going to go to bed uh so I&amp;#39;m just GNA</text><text start="755.76" dur="3.96">slowly get things ready and uh I&amp;#39;m going</text><text start="758.199" dur="4.041">to show you a little bit about the</text><text start="759.72" dur="2.52">shelter</text><text start="777.56" dur="4.079">here all right here&amp;#39;s a real popular</text><text start="780.16" dur="3.119">trick you take some boiling water and</text><text start="781.639" dur="3.521">you put it in one of these hard plastic</text><text start="783.279" dur="4.321">thermoses and then you stick it in your</text><text start="785.16" dur="4.96">sleeping bag and it warms your sleeping</text><text start="787.6" dur="4.12">bag up really nicely the one thing I</text><text start="790.12" dur="5.159">really don&amp;#39;t like about this trick</text><text start="791.72" dur="5.679">though is that if that bottle leaks oh</text><text start="795.279" dur="4.161">man you are in deep trouble so you</text><text start="797.399" dur="6.081">really really want to make sure that the</text><text start="799.44" dur="6.32">lid&amp;#39;s on properly and then you got zero</text><text start="803.48" dur="4.44">leakage it&amp;#39;ll be nice and toasty when</text><text start="805.76" dur="3.639">you&amp;#39;re ready to get inside all right</text><text start="807.92" dur="3.8">let&amp;#39;s go and measure how effici our</text><text start="809.399" dur="4.481">shelter is today so it looks like we&amp;#39;re</text><text start="811.72" dur="4.119">about 16째 out here in the shelter so</text><text start="813.88" dur="4.44">really similar temp to what we had last</text><text start="815.839" dur="5.841">time so it&amp;#39;s supposed to get down to 6째</text><text start="818.32" dur="5.56">tonight you can see we got about 38째 fah</text><text start="821.68" dur="3.959">here in the shelter definitely cooler</text><text start="823.88" dur="3.92">than my last shelter but better than</text><text start="825.639" dur="5.801">being outside all right down here on</text><text start="827.8" dur="6.399">Jacob&amp;#39;s bed we&amp;#39;ve got about 24째 fah here</text><text start="831.44" dur="5.639">so significantly colder here on the</text><text start="834.199" dur="5.401">bottom luckily he&amp;#39;s got Caribou hides</text><text start="837.079" dur="4.081">hand warmers and a - 255</text><text start="839.6" dur="4.239">bag</text><text start="841.16" dur="4.76">y well despite all the improvements I</text><text start="843.839" dur="4.761">made to this shelter I don&amp;#39;t think it&amp;#39;s</text><text start="845.92" dur="4.4">a better shelter it&amp;#39;s colder noticeably</text><text start="848.6" dur="4.12">colder in here and that&amp;#39;s because it&amp;#39;s</text><text start="850.32" dur="4.759">more spacious I accidentally set the</text><text start="852.72" dur="5.32">tripod up about a foot and a half</text><text start="855.079" dur="5.44">further back than where it was last time</text><text start="858.04" dur="4.4">and so I&amp;#39;ve got a lot more volume in</text><text start="860.519" dur="4.201">here and the fire just doesn&amp;#39;t do as</text><text start="862.44" dur="4.16">good of a job heating it up but the good</text><text start="864.72" dur="3.96">part is that the the bed&amp;#39;s higher so</text><text start="866.6" dur="4.76">that Jacob&amp;#39;s got room to sleep out of</text><text start="868.68" dur="4.88">the snow and that&amp;#39;s a huge deal but also</text><text start="871.36" dur="4.52">it means the bed&amp;#39;s higher so you can&amp;#39;t</text><text start="873.56" dur="3.639">sit on the bed and use it like a bench</text><text start="875.88" dur="3.56">in front of the fire when you&amp;#39;re not</text><text start="877.199" dur="3.76">sleeping which is also another downside</text><text start="879.44" dur="3.839">so that&amp;#39;s why we&amp;#39;re kneeling on the</text><text start="880.959" dur="4.24">ground over here which is hard on my old</text><text start="883.279" dur="3.721">back these are the little details I&amp;#39;m</text><text start="885.199" dur="4.08">constantly working on when I build these</text><text start="887" dur="7.16">shelters there&amp;#39;s so many little finicky</text><text start="889.279" dur="4.881">details that you need to watch out for</text><text start="904.72" dur="4.359">all right going to hang my socks up to</text><text start="906.24" dur="5.44">dry before I go to bed warm dry socks</text><text start="909.079" dur="2.601">that feels</text><text start="921.12" dur="5.279">good good morning at 7 a.m. and I&amp;#39;m deep</text><text start="924.399" dur="6.56">inside my sleeping</text><text start="926.399" dur="4.56">bag if I need to get out and build a</text><text start="942.279" dur="4.081">fire all right well I guess it&amp;#39;s time to</text><text start="944.44" dur="4">get some breakfast going but a lot of my</text><text start="946.36" dur="4">ingredients are frozen so we got to thaw</text><text start="948.44" dur="5.12">that out for we just put this Frozen</text><text start="950.36" dur="6.08">block of cream here in this hot water</text><text start="953.56" dur="7.36">bath sit it by the fire it&amp;#39;ll be thought</text><text start="956.44" dur="4.48">out in about 5 minutes all right</text><text start="961.759" dur="3.481">nice and liquid</text><text start="1018.24" dur="4.279">hey bud</text><text start="1019.6" dur="7">dad would you like some</text><text start="1022.519" dur="8.56">bacon no you want some</text><text start="1026.6" dur="4.479">oatmeal oh show</text><text start="1032.839" dur="6.041">okay you want me to set it right there</text><text start="1035.559" dur="3.321">yeah s didn&amp;#39;t wait</text><text start="1042" dur="4.88">to well it was definitely a little nippy</text><text start="1044.36" dur="4.92">last night but uh we did okay shelter</text><text start="1046.88" dur="4.12">definitely got the job done now we got</text><text start="1049.28" dur="3.08">some food in our stomachs and I think</text><text start="1051" dur="4.88">we&amp;#39;re going to go and get everything</text><text start="1052.36" dur="6">slowly packed up but Jake really really</text><text start="1055.88" dur="6.12">wants to go hunting and shoot the 22</text><text start="1058.36" dur="3.64">rifle a little bit</text><text start="1080.679" dur="4.201">well she&amp;#39;s been a good shelter for us</text><text start="1082.44" dur="4.4">just a little bit big but next couple</text><text start="1084.88" dur="5.08">snowfalls we&amp;#39;ll fill in those gaps in</text><text start="1086.84" dur="6.079">the wall and uh it&amp;#39;ll be a lot more</text><text start="1089.96" dur="2.959">airtight next</text><text start="1098.84" dur="6.48">time Hey Jake you want to shoot the 22</text><text start="1101.88" dur="8.24">you want to shoot the gun</text><text start="1105.32" dur="4.8">no okay see that little St</text><text start="1114" dur="6.4">oh there&amp;#39;s more boy you see see that put</text><text start="1117.6" dur="2.8">the holes right</text><text start="1123.08" dur="3.079">there all right when we walk back to the</text><text start="1125.24" dur="3.36">car we&amp;#39;re going to look for some</text><text start="1126.159" dur="4.241">Snowshoe hair they&amp;#39;re a rabbit that</text><text start="1128.6" dur="3.28">changes color they turn white in the</text><text start="1130.4" dur="3.639">winter time and they have little black</text><text start="1131.88" dur="4.32">noses little black eyes and the rest of</text><text start="1134.039" dur="5.12">them&amp;#39;s all white so they&amp;#39;re really</text><text start="1136.2" dur="6.719">camouflaged I want to do a hunt in my</text><text start="1139.159" dur="3.76">SWAT all right here we</text><text start="1143.919" dur="6.24">go we just got to go really slow through</text><text start="1146.76" dur="5.76">the woods and take our time the old rule</text><text start="1150.159" dur="4.121">of thumb is that if you&amp;#39;re walking fast</text><text start="1152.52" dur="5.639">enough to stay warm you&amp;#39;re going too</text><text start="1154.28" dur="6.6">fast you got to go real slow and look</text><text start="1158.159" dur="2.721">under every</text><text start="1162.32" dur="5.16">tree I actually seen some tracks some</text><text start="1164.96" dur="4.32">are covered up with a little bit of snow</text><text start="1167.48" dur="3.16">and others are looking fresh</text><text start="1169.28" dur="3.32">you see right there there&amp;#39;s a freshh</text><text start="1170.64" dur="3.88">track right there that&amp;#39;s the hind feet</text><text start="1172.6" dur="4.959">those are the front feet he&amp;#39;s heading</text><text start="1174.52" dur="5.88">this way and you can see there&amp;#39;s fresh</text><text start="1177.559" dur="5.6">tracks on top of old tracks so this is a</text><text start="1180.4" dur="4.88">spot he goes quite frequently might not</text><text start="1183.159" dur="4.801">be a bad place to put a snare you want</text><text start="1185.28" dur="4.279">to go back to the car all right guys I</text><text start="1187.96" dur="4.199">think it&amp;#39;s time to call it this is a</text><text start="1189.559" dur="4.721">very short-lived rabbit hunting trip but</text><text start="1192.159" dur="3.561">sometimes those are the funnest ones</text><text start="1194.28" dur="3.16">well guys I hope you enjoyed watching</text><text start="1195.72" dur="3.16">this video as much as we enjoyed filming</text><text start="1197.44" dur="2.92">it if you want to see more camp and</text><text start="1198.88" dur="2.88">adventure videos from the outdoor Boys</text><text start="1200.36" dur="3.36">YouTube channel check out our camping</text><text start="1201.76" dur="3.799">and Adventure playlist with over 60</text><text start="1203.72" dur="3.88">videos of our camping Adventures around</text><text start="1205.559" dur="6.161">the world I&amp;#39;ll put a link in the video</text><text start="1207.6" dur="6.199">description below and don&amp;#39;t forget to</text><text start="1211.72" dur="3.6">subscribe if you like this video don&amp;#39;t</text><text start="1213.799" dur="3">forget to check out the outdoor Boys</text><text start="1215.32" dur="3.44">YouTube channel where we have hundreds</text><text start="1216.799" dur="3.961">of videos just like this and don&amp;#39;t</text><text start="1218.76" dur="3.72">forget to click subscribe so you can see</text><text start="1220.76" dur="4.12">other great videos every Saturday</text><text start="1222.48" dur="5.16">morning and hit that Bell button you&amp;#39;ll</text><text start="1224.88" dur="8.279">get notifications thanks for</text><text start="1227.64" dur="5.519">watching you have fun Bud uhhuh good</text></transcript>