<?xml version="1.0" encoding="utf-8" ?><transcript><text start="0" dur="3.48">Luke and Jake here at the outdoor Boys</text><text start="1.68" dur="4.32">YouTube channel and we&amp;#39;re here in Alaska</text><text start="3.48" dur="5.1">we&amp;#39;re chopping a lot of wood making</text><text start="6" dur="5.599">shelters and eating great food you</text><text start="8.58" dur="3.019">having a good time bud yeah</text><text start="11.88" dur="6.79">[Music]</text><text start="28.8" dur="3.86">Hey Jake you doing good yeah</text><text start="34.5" dur="3">oh</text><text start="41.7" dur="3.019">you good yeah</text><text start="45.54" dur="2.06">yeah</text><text start="48.18" dur="4.02">hey Jacobs give me a high five I&amp;#39;m</text><text start="50.219" dur="4.621">impressed you snow shoot a long way bud</text><text start="52.2" dur="4.679">yeah</text><text start="54.84" dur="5.899">you didn&amp;#39;t rest that much should we</text><text start="56.879" dur="3.86">start getting cam set up yep</text><text start="65.46" dur="3.54">really</text><text start="67.02" dur="5.24">here go like that</text><text start="69" dur="3.26">this one&amp;#39;s heavy but</text><text start="76.08" dur="3.78">get all that snow off our bed all right</text><text start="78.42" dur="2.879">guys this is me and Jacob shelter for</text><text start="79.86" dur="3.6">the night I want to finish it up I want</text><text start="81.299" dur="4.021">to go ahead and put some walls on it and</text><text start="83.46" dur="3.96">get it all battened down because it&amp;#39;s a</text><text start="85.32" dur="3.42">lot windier today so we&amp;#39;re gonna be a</text><text start="87.42" dur="3">lot more exposed to the element well</text><text start="88.74" dur="3.72">finding dead trees a cut won&amp;#39;t be a</text><text start="90.42" dur="4.14">problem about nine out of ten trees here</text><text start="92.46" dur="4.08">are dead already in the summertime this</text><text start="94.56" dur="3.419">place is a massive forest fire risk so</text><text start="96.54" dur="4.399">thinning out some of these dead trees</text><text start="97.979" dur="2.96">won&amp;#39;t be a bad thing</text><text start="102.56" dur="3.239">that one</text><text start="108.39" dur="3.189">[Applause]</text><text start="111.899" dur="2.241">okay</text><text start="136.14" dur="5.28">how you doing Jake you getting cold</text><text start="138.66" dur="3.659">what&amp;#39;s cold your hands yeah let me see</text><text start="141.42" dur="2.7">your glass</text><text start="142.319" dur="4.5">okay go</text><text start="144.12" dur="4.44">we&amp;#39;re gonna stick him in Daddy&amp;#39;s pocket</text><text start="146.819" dur="3.981">to get them warmed up we&amp;#39;ve got some</text><text start="148.56" dur="5.039">backup gloves</text><text start="150.8" dur="4.36">they are mittens one of your gloves dry</text><text start="153.599" dur="3.121">in my pocket when those feels better</text><text start="155.16" dur="3.799">then we can switch your gloves back if</text><text start="156.72" dur="2.239">you want</text><text start="163.92" dur="2.24">foreign</text><text start="194.819" dur="4.56">hey Jacob are you feeling a little cold</text><text start="197.099" dur="4.941">you want me to make a little bed for you</text><text start="199.379" dur="2.661">okay</text><text start="204.72" dur="3.42">we&amp;#39;re gonna take off your snow shoes</text><text start="206.34" dur="3.539">I&amp;#39;ve taken my boys camping in some</text><text start="208.14" dur="4.2">pretty gnarly conditions and one thing</text><text start="209.879" dur="5.101">I&amp;#39;ve learned never skimp on the kids</text><text start="212.34" dur="4.44">sleeping bag because if all else fails</text><text start="214.98" dur="4.339">you can always put them in their</text><text start="216.78" dur="2.539">sleeping bag</text><text start="224.34" dur="5.479">Hey Jake you feeling better</text><text start="226.56" dur="3.259">you like your sleeping bag</text><text start="241.56" dur="3.38">your feet nice and toasty</text><text start="250.739" dur="3.541">like that you ready for some hot dogs</text><text start="253.14" dur="4.08">yeah</text><text start="254.28" dur="5.54">my mom&amp;#39;s your mouse stick ready</text><text start="257.22" dur="6.479">all right</text><text start="259.82" dur="5.74">you&amp;#39;re doing a good job with that Jake</text><text start="263.699" dur="4.521">you like your hot dog</text><text start="265.56" dur="2.66">yes</text><text start="270.36" dur="4.399">that&amp;#39;s hard to beat a hot dog over a</text><text start="272.34" dur="2.419">campfire</text><text start="280.259" dur="3.781">you nice and toasty in your sleeping bag</text><text start="281.82" dur="4.7">you want me to get rid of the smoke</text><text start="284.04" dur="2.48">okay</text><text start="287.22" dur="6.14">I got Jacob fed and warm now I need to</text><text start="289.8" dur="3.56">go ahead and process all this wood</text><text start="295.139" dur="2.181">foreign</text><text start="300.44" dur="4.479">thing I wanted to change about this fort</text><text start="302.58" dur="5.72">after my last camp out was I want to</text><text start="304.919" dur="3.381">make this platform a little wider</text><text start="328.38" dur="3">foreign</text><text start="353.16" dur="4.2">nice little pile of Timber there</text><text start="355.44" dur="3.84">Jakey a little hungry</text><text start="357.36" dur="3.6">you know what this is</text><text start="359.28" dur="3.12">it&amp;#39;s cookie dough that&amp;#39;s what the</text><text start="360.96" dur="2.05">cookies look like before you put them in</text><text start="362.4" dur="6.519">the oven</text><text start="363.01" dur="5.909">[Music]</text><text start="370.74" dur="3.14">it&amp;#39;s down a little bit</text><text start="391.5" dur="3">foreign</text><text start="399.74" dur="4.739">what do you think Jake is that pretty</text><text start="401.819" dur="2.66">cozy in there</text><text start="419.58" dur="2.66">like</text><text start="429.319" dur="3.66">how are we gonna cook</text><text start="441.78" dur="3">harder</text><text start="446.039" dur="3">whoa</text><text start="451.139" dur="3.96">bye</text><text start="453.479" dur="3.66">well I&amp;#39;ve been working like a dog from</text><text start="455.099" dur="3.481">sunrise to sunset but unfortunately</text><text start="457.139" dur="4.201">that&amp;#39;s not a very long time here in</text><text start="458.58" dur="5.48">Alaska gotta bust out my lamps a little</text><text start="461.34" dur="2.72">bit ready too</text><text start="474.96" dur="3.42">I&amp;#39;ll tell you these ice fishing sleds</text><text start="476.699" dur="3.661">make really good beds for little boys</text><text start="478.38" dur="3.84">you put them on a couple logs so they&amp;#39;re</text><text start="480.36" dur="4.94">up off the ice just put a little foam</text><text start="482.22" dur="5.4">mat in the bottom of this thing</text><text start="485.3" dur="4.56">now that&amp;#39;ll make a cozy little bed</text><text start="487.62" dur="2.24">tonight</text><text start="491.58" dur="3.679">you probably need a pillow huh</text><text start="495.96" dur="3.9">you want a little headlamp</text><text start="498.34" dur="5.24">[Music]</text><text start="499.86" dur="5.82">yes now first off they they are scared</text><text start="503.58" dur="5.28">of people because people kill wolves</text><text start="505.68" dur="6.18">don&amp;#39;t you worry</text><text start="508.86" dur="4.26">slippers little camping booties to keep</text><text start="511.86" dur="3.919">your feet warm you can wear these in</text><text start="513.12" dur="2.659">your sleeping bag</text><text start="517.26" dur="6.86">yeah see no cold toes I think we should</text><text start="520.979" dur="3.141">build a fire don&amp;#39;t you</text><text start="528.92" dur="5.62">oh wow this shelter just jumped like 20</text><text start="532.2" dur="3.96">degrees it is so warm in here</text><text start="534.54" dur="4.28">but I gotta keep this fire mellow I</text><text start="536.16" dur="4.799">don&amp;#39;t want to melt my tarp</text><text start="538.82" dur="3.82">well me and Jake are sitting here around</text><text start="540.959" dur="3.241">the fire and we&amp;#39;re having a conversation</text><text start="542.64" dur="4.319">about wolves what do you think about</text><text start="544.2" dur="4.5">wolves Jake scary you worried about any</text><text start="546.959" dur="3.601">wolves coming and getting us yeah did</text><text start="548.7" dur="4.139">Daddy tell you you&amp;#39;re safe</text><text start="550.56" dur="5.82">do you believe Daddy</text><text start="552.839" dur="5.281">no the wolves are scared of people will</text><text start="556.38" dur="3.54">stay far away especially if you have a</text><text start="558.12" dur="3.6">campfire the biggest danger around here</text><text start="559.92" dur="4.14">is Moose but just give them enough space</text><text start="561.72" dur="4.26">and they&amp;#39;ll leave you alone oh that fire</text><text start="564.06" dur="4.32">was roaring it was getting to be a bit</text><text start="565.98" dur="4.62">much in this shelter so I went ahead and</text><text start="568.38" dur="3.54">moved it outside and took some of the</text><text start="570.6" dur="2.58">coals and put them right here I&amp;#39;m gonna</text><text start="571.92" dur="3.359">go ahead and start cooking some dinner</text><text start="573.18" dur="3.54">all right as usual I got a little</text><text start="575.279" dur="3.481">something special prepared for dinner</text><text start="576.72" dur="5.66">we&amp;#39;re gonna have some Philly cheesesteak</text><text start="578.76" dur="3.62">sandwiches this is gonna be good</text><text start="590.22" dur="2.239">foreign</text><text start="624.3" dur="3.06">huh</text><text start="625.92" dur="3.479">all right we&amp;#39;re gonna get Jacob some</text><text start="627.36" dur="5">food hey Jacob</text><text start="629.399" dur="2.961">Jacob buddy</text><text start="632.42" dur="5.62">[Music]</text><text start="634.32" dur="6.3">oh we we lost you there bud you okay</text><text start="638.04" dur="5.16">how about a big sandwich</text><text start="640.62" dur="3.719">yeah that sounds good what do you think</text><text start="643.2" dur="4.04">of that</text><text start="644.339" dur="2.901">does that look good</text><text start="649.74" dur="4.32">off</text><text start="652.079" dur="5.421">I like this you like this Jake</text><text start="654.06" dur="3.44">yeah this is hitting the spot</text><text start="658.38" dur="3.98">I think I might need to have another one</text><text start="660.12" dur="2.24">of those</text><text start="663.959" dur="4.461">all right I got something a little</text><text start="665.279" dur="3.141">special for dessert here</text><text start="677.6" dur="7.419">oh look at that it&amp;#39;s got strawberries</text><text start="681.06" dur="6.959">raspberries blackberries blueberries</text><text start="685.019" dur="3">cream</text><text start="688.26" dur="3.96">look at this</text><text start="689.579" dur="4.981">we got pie for you you want me to spoon</text><text start="692.22" dur="7.14">it into your mouth just because I love</text><text start="694.56" dur="7.2">you so much and you&amp;#39;re so tired</text><text start="699.36" dur="3.979">well you like you like dad&amp;#39;s booting pie</text><text start="701.76" dur="3.48">into your mouth</text><text start="703.339" dur="3.881">ah</text><text start="705.24" dur="5.219">yeah we don&amp;#39;t we don&amp;#39;t feed you pie in</text><text start="707.22" dur="5.4">bed at home do we is that good yeah</text><text start="710.459" dur="3.421">there&amp;#39;s no point leaving but leftovers</text><text start="712.62" dur="3.899">right</text><text start="713.88" dur="4.22">oh that was good</text><text start="716.519" dur="7.32">oh</text><text start="718.1" dur="7.72">hold on I got you oh that was good</text><text start="723.839" dur="4.021">all right guys I&amp;#39;m gonna read Jacob some</text><text start="725.82" dur="3.84">stories my dad used to read to me and my</text><text start="727.86" dur="3.419">brother when we were out camping this is</text><text start="729.66" dur="3.72">a collection of true bear stories from</text><text start="731.279" dur="3.841">around Alaska some of these stories are</text><text start="733.38" dur="3.959">a little bit intense so I&amp;#39;m gonna try to</text><text start="735.12" dur="3.839">pick an age-appropriate one here the</text><text start="737.339" dur="3.541">bear then lunged at him and they</text><text start="738.959" dur="4.38">embraced in a death struggle the man</text><text start="740.88" dur="4.44">using his knife and the bear it&amp;#39;s fangs</text><text start="743.339" dur="3.661">and Claws well we&amp;#39;ve had a good time</text><text start="745.32" dur="4.38">reading stories and eating whipped cream</text><text start="747" dur="6.62">but Jacob&amp;#39;s falling asleep and I think</text><text start="749.7" dur="3.92">it&amp;#39;s time for me to get my bed ready too</text><text start="754.32" dur="2.6">foreign</text><text start="770.459" dur="4.5">guys I&amp;#39;m pretty proud with the progress</text><text start="772.32" dur="4.86">I made on the shelter and I&amp;#39;ve got a lot</text><text start="774.959" dur="4.201">to do tomorrow so we&amp;#39;re gonna have a</text><text start="777.18" dur="3.719">full day full day tomorrow but I better</text><text start="779.16" dur="2.82">get some sleep I&amp;#39;ll see you guys in the</text><text start="780.899" dur="2.761">morning</text><text start="781.98" dur="3.539">well good morning it&amp;#39;s about an hour</text><text start="783.66" dur="3">before Sunrise it&amp;#39;s me and Jake are</text><text start="785.519" dur="3.661">doing well</text><text start="786.66" dur="4.799">it&amp;#39;s a little cold in here but uh we&amp;#39;re</text><text start="789.18" dur="5">gonna get a fire started get all nice</text><text start="791.459" dur="2.721">and toasty again</text><text start="799.56" dur="4.14">did you get attacked by wolves</text><text start="802.32" dur="3.18">all right Jake you want to get some</text><text start="803.7" dur="4.28">breakfast</text><text start="805.5" dur="6.44">we&amp;#39;ve got little uh raspberry strudels</text><text start="807.98" dur="3.96">and chocolate croissants</text><text start="813.899" dur="2.781">because we can</text><text start="816.959" dur="2.661">there you go</text><text start="820.04" dur="4.72">watch my fingers</text><text start="822.72" dur="3.96">I also got some chicken and apple uh</text><text start="824.76" dur="4.199">breakfast sausages here we&amp;#39;re gonna cook</text><text start="826.68" dur="4.5">those up I also got a couple eggs here</text><text start="828.959" dur="3.301">we&amp;#39;re gonna cook those by the fire stick</text><text start="831.18" dur="3.86">goes</text><text start="832.26" dur="2.78">right there</text><text start="837.3" dur="2.36">what</text><text start="840.54" dur="2.84">there we go</text><text start="846.66" dur="3.239">well listen I got a bit of building to</text><text start="848.519" dur="3.301">do today so I&amp;#39;m gonna go ahead and clean</text><text start="849.899" dur="4.341">this stuff up and uh then we&amp;#39;re gonna</text><text start="851.82" dur="2.42">get to work</text><text start="859.74" dur="2.539">foreign</text><text start="886.62" dur="3">foreign</text><text start="916.32" dur="2.48">foreign</text><text start="948.899" dur="3">foreign</text><text start="983.88" dur="3">foreign</text><text start="1012.759" dur="3.961">all right let&amp;#39;s test it out</text><text start="1019.399" dur="3">foreign</text><text start="1029.56" dur="4.6">[Applause]</text><text start="1032.179" dur="4.461">now I just need to do a little trim up I</text><text start="1034.16" dur="6.98">need to make these edges nice and clean</text><text start="1036.64" dur="4.5">make these logs all the same length</text><text start="1055.039" dur="3">foreign</text><text start="1076.12" dur="5.08">well not too shabby that is a sharp</text><text start="1079.46" dur="4.32">looking shelter right there</text><text start="1081.2" dur="3.839">yeah I&amp;#39;m proud of that yeah we pulled</text><text start="1083.78" dur="3.18">the tarp over the top that thing will</text><text start="1085.039" dur="3.421">get sealed up really good I&amp;#39;m pretty</text><text start="1086.96" dur="3.54">happy with the progress we&amp;#39;ve made today</text><text start="1088.46" dur="4.02">unfortunately I&amp;#39;m not going to get a</text><text start="1090.5" dur="3.72">chance to camp in it tonight</text><text start="1092.48" dur="4.26">because Jacob do you want to go home and</text><text start="1094.22" dur="4.38">see Mama yeah yeah I got a little bit</text><text start="1096.74" dur="3.36">left I want to do on the shelter so I</text><text start="1098.6" dur="3.74">think I&amp;#39;ll save that for my next camp</text><text start="1100.1" dur="2.24">out</text><text start="1105.14" dur="3.539">now one thing I&amp;#39;ve got to finish when I</text><text start="1106.88" dur="4.28">get back is I gotta wall in this whole</text><text start="1108.679" dur="2.481">backside</text><text start="1116.9" dur="5.72">you good yeah you like it when you write</text><text start="1119.72" dur="2.9">out in your sleeping bag</text><text start="1123.74" dur="4.819">oh</text><text start="1125.72" dur="5.699">foreign</text><text start="1128.559" dur="4.36">for today but don&amp;#39;t forget to click</text><text start="1131.419" dur="3.421">subscribe we put out new videos every</text><text start="1132.919" dur="4.26">Saturday morning and we&amp;#39;ll be back to</text><text start="1134.84" dur="3.719">camp and finish this shelter and if you</text><text start="1137.179" dur="2.821">want to see my previous video where I</text><text start="1138.559" dur="2.821">started this shelter I&amp;#39;ll put a link to</text><text start="1140" dur="3.9">that video in the video description</text><text start="1141.38" dur="3.84">below alright guys see you later if you</text><text start="1143.9" dur="2.82">like this video don&amp;#39;t forget to check</text><text start="1145.22" dur="3.24">out the outdoor Boys YouTube channel</text><text start="1146.72" dur="3.6">where we have hundreds of videos just</text><text start="1148.46" dur="3.719">like this and don&amp;#39;t forget to click</text><text start="1150.32" dur="4.38">subscribe so you can see other great</text><text start="1152.179" dur="4.38">videos every Saturday morning hit that</text><text start="1154.7" dur="3.93">Bell button you&amp;#39;ll get notifications</text><text start="1156.559" dur="4.44">thanks for watching</text><text start="1158.63" dur="2.369">[Music]</text></transcript>